[
  {
    "id": "leb_2peter_1_1",
    "translation": "LEB",
    "book": "2peter",
    "bookName": "2 Peter",
    "chapter": 1,
    "verse": 1,
    "text": "Simeon Peter, a slave and apostle of Jesus Christ, to those who have obtained a faith equal in value to ours by the righteousness of our God and Savior Jesus Christ.",
    "paragraph": 1,
    "speaker": "Narrator",
    "isRedLetter": false
  },
  {
    "id": "leb_2peter_1_2",
    "translation": "LEB",
    "book": "2peter",
    "bookName": "2 Peter",
    "chapter": 1,
    "verse": 2,
    "text": "May grace and peace be multiplied to you in the knowledge of God and of Jesus our Lord,",
    "paragraph": 1,
    "speaker": "Narrator",
    "isRedLetter": false
  },
  {
    "id": "leb_2peter_1_3",
    "translation": "LEB",
    "book": "2peter",
    "bookName": "2 Peter",
    "chapter": 1,
    "verse": 3,
    "text": "because his divine power has bestowed on us all things that are necessary for life and godliness, through the knowledge of the one who called us by his own glory and excellence of character,",
    "paragraph": 1,
    "speaker": "Narrator",
    "isRedLetter": false
  },
  {
    "id": "leb_2peter_1_4",
    "translation": "LEB",
    "book": "2peter",
    "bookName": "2 Peter",
    "chapter": 1,
    "verse": 4,
    "text": "through which things he has bestowed on us his precious and very great promises, so that through these you may become sharers of the divine nature after escaping from the corruption that is in the world because of evil desire,",
    "paragraph": 1,
    "speaker": "Narrator",
    "isRedLetter": false
  },
  {
    "id": "leb_2peter_1_5",
    "translation": "LEB",
    "book": "2peter",
    "bookName": "2 Peter",
    "chapter": 1,
    "verse": 5,
    "text": "and for this same reason, and by applying all diligence, supply with your faith excellence of character, and with excellence of character, knowledge,",
    "paragraph": 1,
    "speaker": "Narrator",
    "isRedLetter": false
  },
  {
    "id": "leb_2peter_1_6",
    "translation": "LEB",
    "book": "2peter",
    "bookName": "2 Peter",
    "chapter": 1,
    "verse": 6,
    "text": "and with knowledge, self-control, and with self-control, patient endurance, and with patient endurance, godliness,",
    "paragraph": 2,
    "speaker": "Narrator",
    "isRedLetter": false
  },
  {
    "id": "leb_2peter_1_7",
    "translation": "LEB",
    "book": "2peter",
    "bookName": "2 Peter",
    "chapter": 1,
    "verse": 7,
    "text": "and with godliness, brotherly love, and with brotherly love, love.",
    "paragraph": 2,
    "speaker": "Narrator",
    "isRedLetter": false
  },
  {
    "id": "leb_2peter_1_8",
    "translation": "LEB",
    "book": "2peter",
    "bookName": "2 Peter",
    "chapter": 1,
    "verse": 8,
    "text": "For if these things are yours and are increasing, this does not make you useless or unproductive in the knowledge of our Lord Jesus Christ.",
    "paragraph": 2,
    "speaker": "Narrator",
    "isRedLetter": false
  },
  {
    "id": "leb_2peter_1_9",
    "translation": "LEB",
    "book": "2peter",
    "bookName": "2 Peter",
    "chapter": 1,
    "verse": 9,
    "text": "For the one for whom these things are not present is blind, being nearsighted, having forgotten the cleansing of his former sins.",
    "paragraph": 2,
    "speaker": "Narrator",
    "isRedLetter": false
  },
  {
    "id": "leb_2peter_1_10",
    "translation": "LEB",
    "book": "2peter",
    "bookName": "2 Peter",
    "chapter": 1,
    "verse": 10,
    "text": "Therefore, brothers, be zealous even more to make your calling and election secure, because if you do these things, you will never ever stumble.",
    "paragraph": 2,
    "speaker": "Narrator",
    "isRedLetter": false
  },
  {
    "id": "leb_2peter_1_11",
    "translation": "LEB",
    "book": "2peter",
    "bookName": "2 Peter",
    "chapter": 1,
    "verse": 11,
    "text": "For in this way entrance into the eternal kingdom of our Lord and Savior Jesus Christ will be richly supplied for you.",
    "paragraph": 3,
    "speaker": "Narrator",
    "isRedLetter": false
  },
  {
    "id": "leb_2peter_1_12",
    "translation": "LEB",
    "book": "2peter",
    "bookName": "2 Peter",
    "chapter": 1,
    "verse": 12,
    "text": "Therefore I intend to remind you continually concerning these things, although you know them and are established in the truth that you have.",
    "paragraph": 3,
    "speaker": "Narrator",
    "isRedLetter": false
  },
  {
    "id": "leb_2peter_1_13",
    "translation": "LEB",
    "book": "2peter",
    "bookName": "2 Peter",
    "chapter": 1,
    "verse": 13,
    "text": "But I consider it right, for as long as I am in this habitation, to stir you up by a reminder,",
    "paragraph": 3,
    "speaker": "Narrator",
    "isRedLetter": false
  },
  {
    "id": "leb_2peter_1_14",
    "translation": "LEB",
    "book": "2peter",
    "bookName": "2 Peter",
    "chapter": 1,
    "verse": 14,
    "text": "because I know that the removal of my habitation is imminent, as indeed our Lord Jesus Christ made clear to me.",
    "paragraph": 3,
    "speaker": "Narrator",
    "isRedLetter": false
  },
  {
    "id": "leb_2peter_1_15",
    "translation": "LEB",
    "book": "2peter",
    "bookName": "2 Peter",
    "chapter": 1,
    "verse": 15,
    "text": "And I will also make every effort that you are able at any time, after my departure, to recall these things to mind.",
    "paragraph": 3,
    "speaker": "Narrator",
    "isRedLetter": false
  },
  {
    "id": "leb_2peter_1_16",
    "translation": "LEB",
    "book": "2peter",
    "bookName": "2 Peter",
    "chapter": 1,
    "verse": 16,
    "text": "For we did not make known to you the power and coming of our Lord Jesus Christ by following ingeniously concocted myths, but by being eyewitnesses of that one’s majesty.",
    "paragraph": 4,
    "speaker": "Narrator",
    "isRedLetter": false
  },
  {
    "id": "leb_2peter_1_17",
    "translation": "LEB",
    "book": "2peter",
    "bookName": "2 Peter",
    "chapter": 1,
    "verse": 17,
    "text": "For he received honor and glory from God the Father when a voice such as this was brought to him by the Majestic Glory, “This is my beloved Son, in whom I am well pleased.”",
    "paragraph": 4,
    "speaker": "Narrator",
    "isRedLetter": false
  },
  {
    "id": "leb_2peter_1_18",
    "translation": "LEB",
    "book": "2peter",
    "bookName": "2 Peter",
    "chapter": 1,
    "verse": 18,
    "text": "And we ourselves heard this voice brought from heaven when we were with him on the holy mountain,",
    "paragraph": 4,
    "speaker": "Narrator",
    "isRedLetter": false
  },
  {
    "id": "leb_2peter_1_19",
    "translation": "LEB",
    "book": "2peter",
    "bookName": "2 Peter",
    "chapter": 1,
    "verse": 19,
    "text": "and we possess as more reliable the prophetic word, to which you do well if you pay attention to it as to a lamp shining in a dark place, until the day dawns and the morning star rises in your hearts,",
    "paragraph": 4,
    "speaker": "Narrator",
    "isRedLetter": false
  },
  {
    "id": "leb_2peter_1_20",
    "translation": "LEB",
    "book": "2peter",
    "bookName": "2 Peter",
    "chapter": 1,
    "verse": 20,
    "text": "recognizing this above all, that every prophecy of scripture does not come about from one’s own interpretation,",
    "paragraph": 4,
    "speaker": "Narrator",
    "isRedLetter": false
  },
  {
    "id": "leb_2peter_1_21",
    "translation": "LEB",
    "book": "2peter",
    "bookName": "2 Peter",
    "chapter": 1,
    "verse": 21,
    "text": "for no prophecy was ever produced by the will of man, but men carried along by the Holy Spirit spoke from God.",
    "paragraph": 5,
    "speaker": "Narrator",
    "isRedLetter": false
  },
  {
    "id": "leb_2peter_2_1",
    "translation": "LEB",
    "book": "2peter",
    "bookName": "2 Peter",
    "chapter": 2,
    "verse": 1,
    "text": "But there were also false prophets among the people, as there will be false teachers among you also, who will bring in destructive heresies, even denying the Master who bought them, thus bringing on themselves swift destruction.",
    "paragraph": 1,
    "speaker": "Narrator",
    "isRedLetter": false
  },
  {
    "id": "leb_2peter_2_2",
    "translation": "LEB",
    "book": "2peter",
    "bookName": "2 Peter",
    "chapter": 2,
    "verse": 2,
    "text": "And many will follow their licentious ways, because of whom the way of truth will be reviled.",
    "paragraph": 1,
    "speaker": "Narrator",
    "isRedLetter": false
  },
  {
    "id": "leb_2peter_2_3",
    "translation": "LEB",
    "book": "2peter",
    "bookName": "2 Peter",
    "chapter": 2,
    "verse": 3,
    "text": "And in greediness they will exploit you with false words, whose condemnation from long ago is not idle, and their destruction is not asleep.",
    "paragraph": 1,
    "speaker": "Narrator",
    "isRedLetter": false
  },
  {
    "id": "leb_2peter_2_4",
    "translation": "LEB",
    "book": "2peter",
    "bookName": "2 Peter",
    "chapter": 2,
    "verse": 4,
    "text": "For if God did not spare the angels who sinned, but held them captive in Tartarus with chains of darkness and handed them over to be kept for judgment,",
    "paragraph": 1,
    "speaker": "Narrator",
    "isRedLetter": false
  },
  {
    "id": "leb_2peter_2_5",
    "translation": "LEB",
    "book": "2peter",
    "bookName": "2 Peter",
    "chapter": 2,
    "verse": 5,
    "text": "and did not spare the ancient world, but preserved Noah, a proclaimer of righteousness, and seven others when he brought a flood on the world of the ungodly,",
    "paragraph": 1,
    "speaker": "Narrator",
    "isRedLetter": false
  },
  {
    "id": "leb_2peter_2_6",
    "translation": "LEB",
    "book": "2peter",
    "bookName": "2 Peter",
    "chapter": 2,
    "verse": 6,
    "text": "and condemned the cities of Sodom and Gomorrah to destruction, reducing them to ashes, having appointed them as an example for those who are going to be ungodly,",
    "paragraph": 2,
    "speaker": "Narrator",
    "isRedLetter": false
  },
  {
    "id": "leb_2peter_2_7",
    "translation": "LEB",
    "book": "2peter",
    "bookName": "2 Peter",
    "chapter": 2,
    "verse": 7,
    "text": "and rescued righteous Lot, worn down by the way of life of lawless persons in licentiousness",
    "paragraph": 2,
    "speaker": "Narrator",
    "isRedLetter": false
  },
  {
    "id": "leb_2peter_2_8",
    "translation": "LEB",
    "book": "2peter",
    "bookName": "2 Peter",
    "chapter": 2,
    "verse": 8,
    "text": "(for that righteous man, as he lived among them day after day, was tormenting his righteous soul by the lawless deeds he was seeing and hearing),",
    "paragraph": 2,
    "speaker": "Narrator",
    "isRedLetter": false
  },
  {
    "id": "leb_2peter_2_9",
    "translation": "LEB",
    "book": "2peter",
    "bookName": "2 Peter",
    "chapter": 2,
    "verse": 9,
    "text": "then the Lord knows how to rescue the godly from trials and to reserve the unrighteous to be punished at the day of judgment,",
    "paragraph": 2,
    "speaker": "Narrator",
    "isRedLetter": false
  },
  {
    "id": "leb_2peter_2_10",
    "translation": "LEB",
    "book": "2peter",
    "bookName": "2 Peter",
    "chapter": 2,
    "verse": 10,
    "text": "and especially those who go after the flesh in defiling lust and who despise authority.\nBold and arrogant, they do not tremble in awe as they blaspheme majestic beings,",
    "paragraph": 2,
    "speaker": "Narrator",
    "isRedLetter": false
  },
  {
    "id": "leb_2peter_2_11",
    "translation": "LEB",
    "book": "2peter",
    "bookName": "2 Peter",
    "chapter": 2,
    "verse": 11,
    "text": "whereas angels, who are greater in strength and power, do not bring against them a demeaning judgment.",
    "paragraph": 3,
    "speaker": "Narrator",
    "isRedLetter": false
  },
  {
    "id": "leb_2peter_2_12",
    "translation": "LEB",
    "book": "2peter",
    "bookName": "2 Peter",
    "chapter": 2,
    "verse": 12,
    "text": "But these persons, like irrational animals born only with natural instincts for capture and killing, blaspheming about things they do not understand, in their destruction will also be destroyed,",
    "paragraph": 3,
    "speaker": "Narrator",
    "isRedLetter": false
  },
  {
    "id": "leb_2peter_2_13",
    "translation": "LEB",
    "book": "2peter",
    "bookName": "2 Peter",
    "chapter": 2,
    "verse": 13,
    "text": "being harmed as the wages of unrighteousness. Considering reveling in the daytime a pleasure, they are stains and blemishes, carousing in their deceitful pleasures when they feast together with you,",
    "paragraph": 3,
    "speaker": "Narrator",
    "isRedLetter": false
  },
  {
    "id": "leb_2peter_2_14",
    "translation": "LEB",
    "book": "2peter",
    "bookName": "2 Peter",
    "chapter": 2,
    "verse": 14,
    "text": "having eyes full of desire for an adulteress and unceasing from sin, enticing unstable persons, and having hearts trained for greediness. Accursed children!",
    "paragraph": 3,
    "speaker": "Narrator",
    "isRedLetter": false
  },
  {
    "id": "leb_2peter_2_15",
    "translation": "LEB",
    "book": "2peter",
    "bookName": "2 Peter",
    "chapter": 2,
    "verse": 15,
    "text": "By leaving the straight path, they have gone astray, because they followed the way of Balaam the son of Bosor, who loved the wages of unrighteousness,",
    "paragraph": 3,
    "speaker": "Narrator",
    "isRedLetter": false
  },
  {
    "id": "leb_2peter_2_16",
    "translation": "LEB",
    "book": "2peter",
    "bookName": "2 Peter",
    "chapter": 2,
    "verse": 16,
    "text": "but received a rebuke for his own lawlessness: a speechless donkey, speaking with a human voice, restrained the prophet’s madness.",
    "paragraph": 4,
    "speaker": "Narrator",
    "isRedLetter": false
  },
  {
    "id": "leb_2peter_2_17",
    "translation": "LEB",
    "book": "2peter",
    "bookName": "2 Peter",
    "chapter": 2,
    "verse": 17,
    "text": "These people are waterless springs and mists driven by a hurricane, for whom the gloom of darkness has been reserved.",
    "paragraph": 4,
    "speaker": "Narrator",
    "isRedLetter": false
  },
  {
    "id": "leb_2peter_2_18",
    "translation": "LEB",
    "book": "2peter",
    "bookName": "2 Peter",
    "chapter": 2,
    "verse": 18,
    "text": "For by speaking high-sounding but empty words, they entice with desires of the flesh and with licentiousness those who are scarcely escaping from those who live in error,",
    "paragraph": 4,
    "speaker": "Narrator",
    "isRedLetter": false
  },
  {
    "id": "leb_2peter_2_19",
    "translation": "LEB",
    "book": "2peter",
    "bookName": "2 Peter",
    "chapter": 2,
    "verse": 19,
    "text": "promising them freedom although they themselves are slaves of depravity. For to whatever someone succumbs, by this he is also enslaved.",
    "paragraph": 4,
    "speaker": "Narrator",
    "isRedLetter": false
  },
  {
    "id": "leb_2peter_2_20",
    "translation": "LEB",
    "book": "2peter",
    "bookName": "2 Peter",
    "chapter": 2,
    "verse": 20,
    "text": "For if, after they have escaped from the defilements of the world through the knowledge of the Lord and Savior Jesus Christ, and they are again entangled in these things and succumb to them, the last state has become worse for them than the first.",
    "paragraph": 4,
    "speaker": "Narrator",
    "isRedLetter": false
  },
  {
    "id": "leb_2peter_2_21",
    "translation": "LEB",
    "book": "2peter",
    "bookName": "2 Peter",
    "chapter": 2,
    "verse": 21,
    "text": "For it would have been better for them not to have known the way of righteousness than having known it, to turn back from the holy commandment that had been delivered to them.",
    "paragraph": 5,
    "speaker": "Narrator",
    "isRedLetter": false
  },
  {
    "id": "leb_2peter_2_22",
    "translation": "LEB",
    "book": "2peter",
    "bookName": "2 Peter",
    "chapter": 2,
    "verse": 22,
    "text": "The statement of the true proverb has happened to them, “A dog returns to its own vomit,” and “A sow, after washing herself, returns to wallowing in the mud.”",
    "paragraph": 5,
    "speaker": "Narrator",
    "isRedLetter": false
  },
  {
    "id": "leb_2peter_3_1",
    "translation": "LEB",
    "book": "2peter",
    "bookName": "2 Peter",
    "chapter": 3,
    "verse": 1,
    "text": "Dear friends, this is already the second letter I am writing to you, in both of which I am attempting to stir up your sincere mind by a reminder,",
    "paragraph": 1,
    "speaker": "Narrator",
    "isRedLetter": false
  },
  {
    "id": "leb_2peter_3_2",
    "translation": "LEB",
    "book": "2peter",
    "bookName": "2 Peter",
    "chapter": 3,
    "verse": 2,
    "text": "to remember the words proclaimed beforehand by the holy prophets and the commandment of the Lord and Savior through your apostles,",
    "paragraph": 1,
    "speaker": "Narrator",
    "isRedLetter": false
  },
  {
    "id": "leb_2peter_3_3",
    "translation": "LEB",
    "book": "2peter",
    "bookName": "2 Peter",
    "chapter": 3,
    "verse": 3,
    "text": "above all knowing this, that in the last days scoffers will come with scoffing, following according to their own desires",
    "paragraph": 1,
    "speaker": "Narrator",
    "isRedLetter": false
  },
  {
    "id": "leb_2peter_3_4",
    "translation": "LEB",
    "book": "2peter",
    "bookName": "2 Peter",
    "chapter": 3,
    "verse": 4,
    "text": "and saying, “Where is the promise of his coming? For ever since the fathers fell asleep, all things have continued just as they have been from the beginning of creation.”",
    "paragraph": 1,
    "speaker": "Narrator",
    "isRedLetter": false
  },
  {
    "id": "leb_2peter_3_5",
    "translation": "LEB",
    "book": "2peter",
    "bookName": "2 Peter",
    "chapter": 3,
    "verse": 5,
    "text": "For when they maintain this, it escapes their notice that the heavens existed long ago and the earth held together out of water and through water by the word of God,",
    "paragraph": 1,
    "speaker": "Narrator",
    "isRedLetter": false
  },
  {
    "id": "leb_2peter_3_6",
    "translation": "LEB",
    "book": "2peter",
    "bookName": "2 Peter",
    "chapter": 3,
    "verse": 6,
    "text": "by means of which things the world that existed at that time was destroyed by being inundated with water.",
    "paragraph": 2,
    "speaker": "Narrator",
    "isRedLetter": false
  },
  {
    "id": "leb_2peter_3_7",
    "translation": "LEB",
    "book": "2peter",
    "bookName": "2 Peter",
    "chapter": 3,
    "verse": 7,
    "text": "But by the same word the present heavens and earth are reserved for fire, being kept for the day of judgment and destruction of ungodly people.",
    "paragraph": 2,
    "speaker": "Narrator",
    "isRedLetter": false
  },
  {
    "id": "leb_2peter_3_8",
    "translation": "LEB",
    "book": "2peter",
    "bookName": "2 Peter",
    "chapter": 3,
    "verse": 8,
    "text": "Now, dear friends, do not let this one thing escape your notice, that one day with the Lord is like a thousand years, and a thousand years is like one day.",
    "paragraph": 2,
    "speaker": "Narrator",
    "isRedLetter": false
  },
  {
    "id": "leb_2peter_3_9",
    "translation": "LEB",
    "book": "2peter",
    "bookName": "2 Peter",
    "chapter": 3,
    "verse": 9,
    "text": "The Lord is not delaying the promise, as some consider slowness, but is being patient toward you, because he does not want any to perish, but all to come to repentance.",
    "paragraph": 2,
    "speaker": "Narrator",
    "isRedLetter": false
  },
  {
    "id": "leb_2peter_3_10",
    "translation": "LEB",
    "book": "2peter",
    "bookName": "2 Peter",
    "chapter": 3,
    "verse": 10,
    "text": "But the day of the Lord will come like a thief, in which the heavens will disappear with a rushing noise, and the celestial bodies will be destroyed by being burned up, and the earth and the deeds done on it will be disclosed.",
    "paragraph": 2,
    "speaker": "Narrator",
    "isRedLetter": false
  },
  {
    "id": "leb_2peter_3_11",
    "translation": "LEB",
    "book": "2peter",
    "bookName": "2 Peter",
    "chapter": 3,
    "verse": 11,
    "text": "Because all these things are being destroyed in this way, what sort of people must you be in holy behavior and godliness,",
    "paragraph": 3,
    "speaker": "Narrator",
    "isRedLetter": false
  },
  {
    "id": "leb_2peter_3_12",
    "translation": "LEB",
    "book": "2peter",
    "bookName": "2 Peter",
    "chapter": 3,
    "verse": 12,
    "text": "while waiting for and hastening the coming of the day of God, because of which the heavens will be destroyed by being burned up and the celestial bodies will melt as they are consumed by heat!",
    "paragraph": 3,
    "speaker": "Narrator",
    "isRedLetter": false
  },
  {
    "id": "leb_2peter_3_13",
    "translation": "LEB",
    "book": "2peter",
    "bookName": "2 Peter",
    "chapter": 3,
    "verse": 13,
    "text": "But according to his promise, we are waiting for new heavens and a new earth in which righteousness resides.",
    "paragraph": 3,
    "speaker": "Narrator",
    "isRedLetter": false
  },
  {
    "id": "leb_2peter_3_14",
    "translation": "LEB",
    "book": "2peter",
    "bookName": "2 Peter",
    "chapter": 3,
    "verse": 14,
    "text": "Therefore, dear friends, because you are waiting for these things, make every effort to be found at peace, spotless and unblemished in him.",
    "paragraph": 3,
    "speaker": "Narrator",
    "isRedLetter": false
  },
  {
    "id": "leb_2peter_3_15",
    "translation": "LEB",
    "book": "2peter",
    "bookName": "2 Peter",
    "chapter": 3,
    "verse": 15,
    "text": "And regard the patience of our Lord as salvation, just as also our dear brother Paul wrote to you, according to the wisdom that was given to him,",
    "paragraph": 3,
    "speaker": "Narrator",
    "isRedLetter": false
  },
  {
    "id": "leb_2peter_3_16",
    "translation": "LEB",
    "book": "2peter",
    "bookName": "2 Peter",
    "chapter": 3,
    "verse": 16,
    "text": "as he does also in all his letters, speaking in them about these things, in which there are some things hard to understand, which the ignorant and unstable distort to their own destruction, as they also do the rest of the scriptures.",
    "paragraph": 4,
    "speaker": "Narrator",
    "isRedLetter": false
  },
  {
    "id": "leb_2peter_3_17",
    "translation": "LEB",
    "book": "2peter",
    "bookName": "2 Peter",
    "chapter": 3,
    "verse": 17,
    "text": "Therefore, dear friends, because you know this beforehand, guard yourselves so that you do not lose your own safe position because you have been led away by the error of lawless persons.",
    "paragraph": 4,
    "speaker": "Narrator",
    "isRedLetter": false
  },
  {
    "id": "leb_2peter_3_18",
    "translation": "LEB",
    "book": "2peter",
    "bookName": "2 Peter",
    "chapter": 3,
    "verse": 18,
    "text": "But grow in the grace and knowledge of our Lord and Savior Jesus Christ. To him be the glory, both now and to the day of eternity. Amen.",
    "paragraph": 4,
    "speaker": "Narrator",
    "isRedLetter": false
  }
]